condconfigparser/__init__.py
condconfigparser/condconfig.py
condconfigparser/exceptions.py
condconfigparser/lexer.py
condconfigparser/parser.py
condconfigparser-1.0.6.dist-info/licenses/AUTHORS
condconfigparser-1.0.6.dist-info/licenses/COPYING
condconfigparser-1.0.6.dist-info/licenses/COPYING.Sphinx
condconfigparser-1.0.6.dist-info/METADATA
condconfigparser-1.0.6.dist-info/WHEEL
condconfigparser-1.0.6.dist-info/top_level.txt
condconfigparser-1.0.6.dist-info/RECORD
