Metadata-Version: 2.4
Name: CondConfigParser
Version: 1.0.6
Summary: Python library for parsing configuration files with conditionals
Author-email: Florent Rougon <f.rougon@frougon.net>
License-Expression: BSD-2-Clause
Project-URL: Homepage, https://frougon.net/projects/CondConfigParser/
Project-URL: Repository, https://github.com/frougon/CondConfigParser
Project-URL: Issues, https://github.com/frougon/CondConfigParser/issues
Keywords: configuration,file,parsing,parser,conditionals,variables,lists
Classifier: Development Status :: 5 - Production/Stable
Classifier: Intended Audience :: Developers
Classifier: Operating System :: OS Independent
Classifier: Programming Language :: Python :: 3
Classifier: Topic :: Software Development :: Libraries :: Python Modules
Requires-Python: >=3.4
License-File: COPYING
License-File: COPYING.Sphinx
License-File: AUTHORS
Dynamic: license-file
